macmoji/__init__.py
macmoji/__main__.py
macmoji/cli/__init__.py
macmoji/cli/create.py
macmoji/cli/main.py
macmoji/config.py
macmoji/converter.py
macmoji/font.py
macmoji/inserter.py
macmoji/utils.py
macmoji-1.0.0.dist-info/METADATA
macmoji-1.0.0.dist-info/WHEEL
macmoji-1.0.0.dist-info/entry_points.txt
macmoji-1.0.0.dist-info/RECORD
