Metadata-Version: 2.1
Name: macmoji
Version: 1.0.0
Summary: Create custom emoji fonts for macOS.
Author: Gustav Odinger
Author-email: 65498475+gustavwilliam@users.noreply.github.com
Requires-Python: >=3.10,<4.0
Classifier: Programming Language :: Python :: 3
Classifier: Programming Language :: Python :: 3.10
Classifier: Programming Language :: Python :: 3.11
Requires-Dist: afdko (>=3.9.6,<4.0.0)
Requires-Dist: cairosvg (>=2.7.0,<3.0.0)
Requires-Dist: fonttools (>=4.40.0,<5.0.0)
Requires-Dist: humanize (>=4.7.0,<5.0.0)
Requires-Dist: pillow (>=10.0.0,<11.0.0)
Requires-Dist: typer[all] (>=0.9.0,<0.10.0)
